LICENSE
MANIFEST.in
README.md
requirements.txt
setup.py
training_rg/__init__.py
training_rg/__version__.py
training_rg/classifiers.py
training_rg/constants.py
training_rg/logger.py
training_rg/sequential.py
training_rg.egg-info/PKG-INFO
training_rg.egg-info/SOURCES.txt
training_rg.egg-info/dependency_links.txt
training_rg.egg-info/entry_points.txt
training_rg.egg-info/requires.txt
training_rg.egg-info/top_level.txt
training_rg.egg-info/zip-safe