Metadata-Version: 1.2
Name: training-rg
Version: 1.1.0
Summary: Training routine generator
Home-page: https://github.com/alexisdevsol89/training_rg
Author: Alexis Torres Valdes
Author-email: alexisdevsol@gmail.com
License: LGPL
Keywords: python
Platform: Linux
Platform: Windows
Platform: MacOS
Classifier: Development Status :: 3 - Alpha
Classifier: Intended Audience :: Other Audience
Classifier: License :: OSI Approved :: GNU Lesser General Public License v2 or later (LGPLv2+)
Classifier: Programming Language :: Python :: 3.6
Classifier: Programming Language :: Python :: Implementation :: CPython
Classifier: Operating System :: POSIX :: Linux
Classifier: Operating System :: Microsoft :: Windows
Classifier: Operating System :: MacOS
Classifier: Topic :: Education :: Testing
Classifier: Topic :: Games/Entertainment
Classifier: Topic :: Other/Nonlisted Topic
Requires-Python: >=3.6
